{
    "features": [
        {
            "type": "Feature",
            "properties": {
                "mag": 2.35,
                "place": "15 km SE of Mineral, CA",
                "time": "2024-05-05 02:38:05.410000",
                "updated": 1714901981349,
                "tz": null,
                "url": "https://earthquake.usgs.gov/earthquakes/eventpage/nc75001526",
                "detail": "https://earthquake.usgs.gov/fdsnws/event/1/query?eventid=nc75001526&format=geojson",
                "felt": null,
                "cdi": null,
                "mmi": null,
                "alert": null,
                "status": "automatic",
                "tsunami": 0,
                "sig": 85,
                "net": "nc",
                "code": "75001526",
                "ids": ",nc75001526,",
                "sources": ",nc,",
                "types": ",nearby-cities,origin,phase-data,",
                "nst": 8,
                "dmin": 0.1293,
                "rms": 0.22,
                "gap": 178,
                "magType": "md",
                "type": "earthquake",
                "title": "M 2.4 - 15 km SE of Mineral, CA"
            },
            "geometry": {
                "type": "Point",
                "coordinates": [
                    -121.434501647949,
                    40.2681655883789,
                    -0.509999990463257
                ]
            },
            "id": "nc75001526"
        },
        {
            "type": "Feature",
            "properties": {
                "mag": 0.22,
                "place": "8 km NW of The Geysers, CA",
                "time": "2024-05-05 02:35:40.720000",
                "updated": 1714901836486,
                "tz": null,
                "url": "https://earthquake.usgs.gov/earthquakes/eventpage/nc75001521",
                "detail": "https://earthquake.usgs.gov/fdsnws/event/1/query?eventid=nc75001521&format=geojson",
                "felt": null,
                "cdi": null,
                "mmi": null,
                "alert": null,
                "status": "automatic",
                "tsunami": 0,
                "sig": 1,
                "net": "nc",
                "code": "75001521",
                "ids": ",nc75001521,",
                "sources": ",nc,",
                "types": ",nearby-cities,origin,phase-data,",
                "nst": 7,
                "dmin": 0.02654,
                "rms": 0.03,
                "gap": 125,
                "magType": "md",
                "type": "earthquake",
                "title": "M 0.2 - 8 km NW of The Geysers, CA"
            },
            "geometry": {
                "type": "Point",
                "coordinates": [
                    -122.820503234863,
                    38.8261680603027,
                    2.39000010490417
                ]
            },
            "id": "nc75001521"
        },
        {
            "type": "Feature",
            "properties": {
                "mag": 0.76,
                "place": "8 km NNW of The Geysers, CA",
                "time": "2024-05-05 02:35:06.500000",
                "updated": 1714901801269,
                "tz": null,
                "url": "https://earthquake.usgs.gov/earthquakes/eventpage/nc75001516",
                "detail": "https://earthquake.usgs.gov/fdsnws/event/1/query?eventid=nc75001516&format=geojson",
                "felt": null,
                "cdi": null,
                "mmi": null,
                "alert": null,
                "status": "automatic",
                "tsunami": 0,
                "sig": 9,
                "net": "nc",
                "code": "75001516",
                "ids": ",nc75001516,",
                "sources": ",nc,",
                "types": ",nearby-cities,origin,phase-data,",
                "nst": 15,
                "dmin": 0.007769,
                "rms": 0.02,
                "gap": 87,
                "magType": "md",
                "type": "earthquake",
                "title": "M 0.8 - 8 km NNW of The Geysers, CA"
            },
            "geometry": {
                "type": "Point",
                "coordinates": [
                    -122.812164306641,
                    38.8310012817383,
                    1.88999998569489
                ]
            },
            "id": "nc75001516"
        },
        {
            "type": "Feature",
            "properties": {
                "mag": 1.3,
                "place": "45 km ENE of Susitna North, Alaska",
                "time": "2024-05-05 02:34:49.177000",
                "updated": 1714901871370,
                "tz": null,
                "url": "https://earthquake.usgs.gov/earthquakes/eventpage/ak0245sja0rh",
                "detail": "https://earthquake.usgs.gov/fdsnws/event/1/query?eventid=ak0245sja0rh&format=geojson",
                "felt": null,
                "cdi": null,
                "mmi": null,
                "alert": null,
                "status": "automatic",
                "tsunami": 0,
                "sig": 26,
                "net": "ak",
                "code": "0245sja0rh",
                "ids": ",ak0245sja0rh,",
                "sources": ",ak,",
                "types": ",origin,phase-data,",
                "nst": null,
                "dmin": null,
                "rms": 0.64,
                "gap": null,
                "magType": "ml",
                "type": "earthquake",
                "title": "M 1.3 - 45 km ENE of Susitna North, Alaska"
            },
            "geometry": {
                "type": "Point",
                "coordinates": [
                    -149.0693,
                    62.3532,
                    10.7
                ]
            },
            "id": "ak0245sja0rh"
        },
        {
            "type": "Feature",
            "properties": {
                "mag": 1.8,
                "place": "57 km S of Whites City, New Mexico",
                "time": "2024-05-05 02:14:07.988000",
                "updated": 1714902706793,
                "tz": null,
                "url": "https://earthquake.usgs.gov/earthquakes/eventpage/tx2024ivce",
                "detail": "https://earthquake.usgs.gov/fdsnws/event/1/query?eventid=tx2024ivce&format=geojson",
                "felt": null,
                "cdi": null,
                "mmi": null,
                "alert": null,
                "status": "automatic",
                "tsunami": 0,
                "sig": 50,
                "net": "tx",
                "code": "2024ivce",
                "ids": ",tx2024ivce,",
                "sources": ",tx,",
                "types": ",origin,phase-data,",
                "nst": 15,
                "dmin": 0.1,
                "rms": 0.3,
                "gap": 71,
                "magType": "ml",
                "type": "earthquake",
                "title": "M 1.8 - 57 km S of Whites City, New Mexico"
            },
            "geometry": {
                "type": "Point",
                "coordinates": [
                    -104.431,
                    31.663,
                    4.5925
                ]
            },
            "id": "tx2024ivce"
        },
        {
            "type": "Feature",
            "properties": {
                "mag": 1.28,
                "place": "1 km NNW of The Geysers, CA",
                "time": "2024-05-05 02:11:19.580000",
                "updated": 1714900376711,
                "tz": null,
                "url": "https://earthquake.usgs.gov/earthquakes/eventpage/nc75001506",
                "detail": "https://earthquake.usgs.gov/fdsnws/event/1/query?eventid=nc75001506&format=geojson",
                "felt": null,
                "cdi": null,
                "mmi": null,
                "alert": null,
                "status": "automatic",
                "tsunami": 0,
                "sig": 25,
                "net": "nc",
                "code": "75001506",
                "ids": ",nc75001506,",
                "sources": ",nc,",
                "types": ",nearby-cities,origin,phase-data,",
                "nst": 24,
                "dmin": 0.01337,
                "rms": 0.03,
                "gap": 62,
                "magType": "md",
                "type": "earthquake",
                "title": "M 1.3 - 1 km NNW of The Geysers, CA"
            },
            "geometry": {
                "type": "Point",
                "coordinates": [
                    -122.76000213623,
                    38.783332824707,
                    3.55999994277954
                ]
            },
            "id": "nc75001506"
        },
        {
            "type": "Feature",
            "properties": {
                "mag": 5.2,
                "place": "96 km NNW of Finschhafen, Papua New Guinea",
                "time": "2024-05-05 01:57:54.490000",
                "updated": 1714901494748,
                "tz": null,
                "url": "https://earthquake.usgs.gov/earthquakes/eventpage/us6000mwg2",
                "detail": "https://earthquake.usgs.gov/fdsnws/event/1/query?eventid=us6000mwg2&format=geojson",
                "felt": 1,
                "cdi": 3.4,
                "mmi": null,
                "alert": null,
                "status": "reviewed",
                "tsunami": 0,
                "sig": 416,
                "net": "us",
                "code": "6000mwg2",
                "ids": ",us6000mwg2,usauto6000mwg2,",
                "sources": ",us,usauto,",
                "types": ",dyfi,internal-moment-tensor,origin,phase-data,",
                "nst": 63,
                "dmin": 3.585,
                "rms": 0.62,
                "gap": 95,
                "magType": "mww",
                "type": "earthquake",
                "title": "M 5.2 - 96 km NNW of Finschhafen, Papua New Guinea"
            },
            "geometry": {
                "type": "Point",
                "coordinates": [
                    147.4095,
                    -5.8052,
                    139.377
                ]
            },
            "id": "us6000mwg2"
        },
        {
            "type": "Feature",
            "properties": {
                "mag": 2.1,
                "place": "7 km S of Talkeetna, Alaska",
                "time": "2024-05-05 01:37:10.180000",
                "updated": 1714898336044,
                "tz": null,
                "url": "https://earthquake.usgs.gov/earthquakes/eventpage/ak0245sip5ca",
                "detail": "https://earthquake.usgs.gov/fdsnws/event/1/query?eventid=ak0245sip5ca&format=geojson",
                "felt": null,
                "cdi": null,
                "mmi": null,
                "alert": null,
                "status": "automatic",
                "tsunami": 0,
                "sig": 68,
                "net": "ak",
                "code": "0245sip5ca",
                "ids": ",ak0245sip5ca,",
                "sources": ",ak,",
                "types": ",origin,phase-data,",
                "nst": null,
                "dmin": null,
                "rms": 0.41,
                "gap": null,
                "magType": "ml",
                "type": "earthquake",
                "title": "M 2.1 - 7 km S of Talkeetna, Alaska"
            },
            "geometry": {
                "type": "Point",
                "coordinates": [
                    -150.0817,
                    62.2584,
                    45.6
                ]
            },
            "id": "ak0245sip5ca"
        },
        {
            "type": "Feature",
            "properties": {
                "mag": 3.74,
                "place": "72 km NE of Cruz Bay, U.S. Virgin Islands",
                "time": "2024-05-05 01:29:18.750000",
                "updated": 1714899332971,
                "tz": null,
                "url": "https://earthquake.usgs.gov/earthquakes/eventpage/pr2024126000",
                "detail": "https://earthquake.usgs.gov/fdsnws/event/1/query?eventid=pr2024126000&format=geojson",
                "felt": null,
                "cdi": null,
                "mmi": null,
                "alert": null,
                "status": "reviewed",
                "tsunami": 0,
                "sig": 215,
                "net": "pr",
                "code": "2024126000",
                "ids": ",pr2024126000,",
                "sources": ",pr,",
                "types": ",origin,phase-data,",
                "nst": 17,
                "dmin": 0.5034,
                "rms": 0.36,
                "gap": 297,
                "magType": "md",
                "type": "earthquake",
                "title": "M 3.7 - 72 km NE of Cruz Bay, U.S. Virgin Islands"
            },
            "geometry": {
                "type": "Point",
                "coordinates": [
                    -64.3851,
                    18.861,
                    8
                ]
            },
            "id": "pr2024126000"
        },
        {
            "type": "Feature",
            "properties": {
                "mag": 5.2,
                "place": "195 km SE of Akutan, Alaska",
                "time": "2024-05-05 01:27:46.321000",
                "updated": 1714901271950,
                "tz": null,
                "url": "https://earthquake.usgs.gov/earthquakes/eventpage/us6000mwfw",
                "detail": "https://earthquake.usgs.gov/fdsnws/event/1/query?eventid=us6000mwfw&format=geojson",
                "felt": null,
                "cdi": null,
                "mmi": 2.564,
                "alert": null,
                "status": "reviewed",
                "tsunami": 0,
                "sig": 416,
                "net": "us",
                "code": "6000mwfw",
                "ids": ",usauto6000mwfw,us6000mwfw,ak0245sin332,",
                "sources": ",usauto,us,ak,",
                "types": ",internal-moment-tensor,moment-tensor,oaf,origin,phase-data,shakemap,",
                "nst": 127,
                "dmin": 1.923,
                "rms": 0.68,
                "gap": 65,
                "magType": "mww",
                "type": "earthquake",
                "title": "M 5.2 - 195 km SE of Akutan, Alaska"
            },
            "geometry": {
                "type": "Point",
                "coordinates": [
                    -163.7635,
                    52.8483,
                    10
                ]
            },
            "id": "us6000mwfw"
        },
        {
            "type": "Feature",
            "properties": {
                "mag": 2.14,
                "place": "2 km E of Maria Antonia, Puerto Rico",
                "time": "2024-05-05 01:12:57.660000",
                "updated": 1714897437810,
                "tz": null,
                "url": "https://earthquake.usgs.gov/earthquakes/eventpage/pr71447728",
                "detail": "https://earthquake.usgs.gov/fdsnws/event/1/query?eventid=pr71447728&format=geojson",
                "felt": null,
                "cdi": null,
                "mmi": null,
                "alert": null,
                "status": "reviewed",
                "tsunami": 0,
                "sig": 70,
                "net": "pr",
                "code": "71447728",
                "ids": ",pr71447728,",
                "sources": ",pr,",
                "types": ",origin,phase-data,",
                "nst": 10,
                "dmin": 0.008189,
                "rms": 0.17,
                "gap": 193,
                "magType": "md",
                "type": "earthquake",
                "title": "M 2.1 - 2 km E of Maria Antonia, Puerto Rico"
            },
            "geometry": {
                "type": "Point",
                "coordinates": [
                    -66.8706666666667,
                    17.9755,
                    16.65
                ]
            },
            "id": "pr71447728"
        },
        {
            "type": "Feature",
            "properties": {
                "mag": 1.4,
                "place": "43 km ENE of Susitna North, Alaska",
                "time": "2024-05-05 01:07:56.169000",
                "updated": 1714896589604,
                "tz": null,
                "url": "https://earthquake.usgs.gov/earthquakes/eventpage/ak0245siiteo",
                "detail": "https://earthquake.usgs.gov/fdsnws/event/1/query?eventid=ak0245siiteo&format=geojson",
                "felt": null,
                "cdi": null,
                "mmi": null,
                "alert": null,
                "status": "automatic",
                "tsunami": 0,
                "sig": 30,
                "net": "ak",
                "code": "0245siiteo",
                "ids": ",ak0245siiteo,",
                "sources": ",ak,",
                "types": ",origin,phase-data,",
                "nst": null,
                "dmin": null,
                "rms": 0.8,
                "gap": null,
                "magType": "ml",
                "type": "earthquake",
                "title": "M 1.4 - 43 km ENE of Susitna North, Alaska"
            },
            "geometry": {
                "type": "Point",
                "coordinates": [
                    -149.1181,
                    62.3532,
                    2.4
                ]
            },
            "id": "ak0245siiteo"
        },
        {
            "type": "Feature",
            "properties": {
                "mag": 1.31,
                "place": "7 km NW of The Geysers, CA",
                "time": "2024-05-05 00:59:12.890000",
                "updated": 1714896050852,
                "tz": null,
                "url": "https://earthquake.usgs.gov/earthquakes/eventpage/nc75001486",
                "detail": "https://earthquake.usgs.gov/fdsnws/event/1/query?eventid=nc75001486&format=geojson",
                "felt": null,
                "cdi": null,
                "mmi": null,
                "alert": null,
                "status": "automatic",
                "tsunami": 0,
                "sig": 26,
                "net": "nc",
                "code": "75001486",
                "ids": ",nc75001486,",
                "sources": ",nc,",
                "types": ",nearby-cities,origin,phase-data,",
                "nst": 27,
                "dmin": 0.006778,
                "rms": 0.06,
                "gap": 56,
                "magType": "md",
                "type": "earthquake",
                "title": "M 1.3 - 7 km NW of The Geysers, CA"
            },
            "geometry": {
                "type": "Point",
                "coordinates": [
                    -122.824333190918,
                    38.8144989013672,
                    3.70000004768372
                ]
            },
            "id": "nc75001486"
        },
        {
            "type": "Feature",
            "properties": {
                "mag": 1.07,
                "place": "2 km ENE of The Geysers, CA",
                "time": "2024-05-05 00:51:43.540000",
                "updated": 1714895600505,
                "tz": null,
                "url": "https://earthquake.usgs.gov/earthquakes/eventpage/nc75001481",
                "detail": "https://earthquake.usgs.gov/fdsnws/event/1/query?eventid=nc75001481&format=geojson",
                "felt": null,
                "cdi": null,
                "mmi": null,
                "alert": null,
                "status": "automatic",
                "tsunami": 0,
                "sig": 18,
                "net": "nc",
                "code": "75001481",
                "ids": ",nc75001481,",
                "sources": ",nc,",
                "types": ",nearby-cities,origin,phase-data,",
                "nst": 7,
                "dmin": 0.00214,
                "rms": 0.01,
                "gap": 151,
                "magType": "md",
                "type": "earthquake",
                "title": "M 1.1 - 2 km ENE of The Geysers, CA"
            },
            "geometry": {
                "type": "Point",
                "coordinates": [
                    -122.735168457031,
                    38.7849998474121,
                    2.19000005722046
                ]
            },
            "id": "nc75001481"
        },
        {
            "type": "Feature",
            "properties": {
                "mag": 2.14,
                "place": "6 km N of Delta, B.C., MX",
                "time": "2024-05-05 00:47:20.970000",
                "updated": 1714896221604,
                "tz": null,
                "url": "https://earthquake.usgs.gov/earthquakes/eventpage/ci40739912",
                "detail": "https://earthquake.usgs.gov/fdsnws/event/1/query?eventid=ci40739912&format=geojson",
                "felt": 1,
                "cdi": 2.2,
                "mmi": null,
                "alert": null,
                "status": "automatic",
                "tsunami": 0,
                "sig": 71,
                "net": "ci",
                "code": "40739912",
                "ids": ",ci40739912,",
                "sources": ",ci,",
                "types": ",dyfi,nearby-cities,origin,phase-data,scitech-link,",
                "nst": 29,
                "dmin": 0.0835,
                "rms": 0.28,
                "gap": 52,
                "magType": "ml",
                "type": "earthquake",
                "title": "M 2.1 - 6 km N of Delta, B.C., MX"
            },
            "geometry": {
                "type": "Point",
                "coordinates": [
                    -115.1988333,
                    32.4133333,
                    7.51
                ]
            },
            "id": "ci40739912"
        },
        {
            "type": "Feature",
            "properties": {
                "mag": 0.7,
                "place": "9 km WSW of Anza, CA",
                "time": "2024-05-05 00:43:50.340000",
                "updated": 1714895244865,
                "tz": null,
                "url": "https://earthquake.usgs.gov/earthquakes/eventpage/ci40739904",
                "detail": "https://earthquake.usgs.gov/fdsnws/event/1/query?eventid=ci40739904&format=geojson",
                "felt": null,
                "cdi": null,
                "mmi": null,
                "alert": null,
                "status": "automatic",
                "tsunami": 0,
                "sig": 8,
                "net": "ci",
                "code": "40739904",
                "ids": ",ci40739904,",
                "sources": ",ci,",
                "types": ",nearby-cities,origin,phase-data,scitech-link,",
                "nst": 23,
                "dmin": 0.04472,
                "rms": 0.13,
                "gap": 66,
                "magType": "ml",
                "type": "earthquake",
                "title": "M 0.7 - 9 km WSW of Anza, CA"
            },
            "geometry": {
                "type": "Point",
                "coordinates": [
                    -116.7556686,
                    33.5110016,
                    5.73
                ]
            },
            "id": "ci40739904"
        },
        {
            "type": "Feature",
            "properties": {
                "mag": 2.59,
                "place": "22 km WSW of Delta, B.C., MX",
                "time": "2024-05-05 00:27:13.740000",
                "updated": 1714894698224,
                "tz": null,
                "url": "https://earthquake.usgs.gov/earthquakes/eventpage/ci40739896",
                "detail": "https://earthquake.usgs.gov/fdsnws/event/1/query?eventid=ci40739896&format=geojson",
                "felt": 1,
                "cdi": 3.1,
                "mmi": null,
                "alert": null,
                "status": "automatic",
                "tsunami": 0,
                "sig": 104,
                "net": "ci",
                "code": "40739896",
                "ids": ",ci40739896,",
                "sources": ",ci,",
                "types": ",dyfi,nearby-cities,origin,phase-data,scitech-link,",
                "nst": 9,
                "dmin": 0.1785,
                "rms": 0.32,
                "gap": 259,
                "magType": "ml",
                "type": "earthquake",
                "title": "M 2.6 - 22 km WSW of Delta, B.C., MX"
            },
            "geometry": {
                "type": "Point",
                "coordinates": [
                    -115.4093333,
                    32.279,
                    -0.01
                ]
            },
            "id": "ci40739896"
        },
        {
            "type": "Feature",
            "properties": {
                "mag": 2.49,
                "place": "18 km WNW of Alberto Oviedo Mota, B.C., MX",
                "time": "2024-05-05 00:27:00.060000",
                "updated": 1714894960507,
                "tz": null,
                "url": "https://earthquake.usgs.gov/earthquakes/eventpage/ci40739888",
                "detail": "https://earthquake.usgs.gov/fdsnws/event/1/query?eventid=ci40739888&format=geojson",
                "felt": 0,
                "cdi": 1,
                "mmi": null,
                "alert": null,
                "status": "automatic",
                "tsunami": 0,
                "sig": 95,
                "net": "ci",
                "code": "40739888",
                "ids": ",ci40739888,",
                "sources": ",ci,",
                "types": ",dyfi,nearby-cities,origin,phase-data,scitech-link,",
                "nst": 33,
                "dmin": 0.142,
                "rms": 0.29,
                "gap": 69,
                "magType": "ml",
                "type": "earthquake",
                "title": "M 2.5 - 18 km WNW of Alberto Oviedo Mota, B.C., MX"
            },
            "geometry": {
                "type": "Point",
                "coordinates": [
                    -115.3531667,
                    32.2648333,
                    -0.05
                ]
            },
            "id": "ci40739888"
        },
        {
            "type": "Feature",
            "properties": {
                "mag": 2.1,
                "place": "55 km S of Whites City, New Mexico",
                "time": "2024-05-05 00:26:51.799000",
                "updated": 1714896540083,
                "tz": null,
                "url": "https://earthquake.usgs.gov/earthquakes/eventpage/tx2024iuyq",
                "detail": "https://earthquake.usgs.gov/fdsnws/event/1/query?eventid=tx2024iuyq&format=geojson",
                "felt": null,
                "cdi": null,
                "mmi": null,
                "alert": null,
                "status": "automatic",
                "tsunami": 0,
                "sig": 68,
                "net": "tx",
                "code": "2024iuyq",
                "ids": ",tx2024iuyq,",
                "sources": ",tx,",
                "types": ",origin,phase-data,",
                "nst": 18,
                "dmin": 0,
                "rms": 0.4,
                "gap": 57,
                "magType": "ml",
                "type": "earthquake",
                "title": "M 2.1 - 55 km S of Whites City, New Mexico"
            },
            "geometry": {
                "type": "Point",
                "coordinates": [
                    -104.427,
                    31.674,
                    4.5424
                ]
            },
            "id": "tx2024iuyq"
        },
        {
            "type": "Feature",
            "properties": {
                "mag": 1.93,
                "place": "18 km WNW of Alberto Oviedo Mota, B.C., MX",
                "time": "2024-05-05 00:26:35.790000",
                "updated": 1714894423789,
                "tz": null,
                "url": "https://earthquake.usgs.gov/earthquakes/eventpage/ci40739880",
                "detail": "https://earthquake.usgs.gov/fdsnws/event/1/query?eventid=ci40739880&format=geojson",
                "felt": null,
                "cdi": null,
                "mmi": null,
                "alert": null,
                "status": "automatic",
                "tsunami": 0,
                "sig": 57,
                "net": "ci",
                "code": "40739880",
                "ids": ",ci40739880,",
                "sources": ",ci,",
                "types": ",nearby-cities,origin,phase-data,scitech-link,",
                "nst": 25,
                "dmin": 0.1435,
                "rms": 0.3,
                "gap": 68,
                "magType": "ml",
                "type": "earthquake",
                "title": "M 1.9 - 18 km WNW of Alberto Oviedo Mota, B.C., MX"
            },
            "geometry": {
                "type": "Point",
                "coordinates": [
                    -115.3493333,
                    32.2678333,
                    -0.05
                ]
            },
            "id": "ci40739880"
        },
        {
            "type": "Feature",
            "properties": {
                "mag": 0.86,
                "place": "9 km E of Moreno Valley, CA",
                "time": "2024-05-05 00:24:12.350000",
                "updated": 1714894314778,
                "tz": null,
                "url": "https://earthquake.usgs.gov/earthquakes/eventpage/ci40739872",
                "detail": "https://earthquake.usgs.gov/fdsnws/event/1/query?eventid=ci40739872&format=geojson",
                "felt": null,
                "cdi": null,
                "mmi": null,
                "alert": null,
                "status": "automatic",
                "tsunami": 0,
                "sig": 11,
                "net": "ci",
                "code": "40739872",
                "ids": ",ci40739872,",
                "sources": ",ci,",
                "types": ",nearby-cities,origin,phase-data,scitech-link,",
                "nst": 19,
                "dmin": 0.044,
                "rms": 0.13,
                "gap": 113,
                "magType": "ml",
                "type": "earthquake",
                "title": "M 0.9 - 9 km E of Moreno Valley, CA"
            },
            "geometry": {
                "type": "Point",
                "coordinates": [
                    -117.1261667,
                    33.9265,
                    13.98
                ]
            },
            "id": "ci40739872"
        },
        {
            "type": "Feature",
            "properties": {
                "mag": 0.76,
                "place": "9 km NW of The Geysers, CA",
                "time": "2024-05-05 00:19:43.390000",
                "updated": 1714893680600,
                "tz": null,
                "url": "https://earthquake.usgs.gov/earthquakes/eventpage/nc75001466",
                "detail": "https://earthquake.usgs.gov/fdsnws/event/1/query?eventid=nc75001466&format=geojson",
                "felt": null,
                "cdi": null,
                "mmi": null,
                "alert": null,
                "status": "automatic",
                "tsunami": 0,
                "sig": 9,
                "net": "nc",
                "code": "75001466",
                "ids": ",nc75001466,",
                "sources": ",nc,",
                "types": ",nearby-cities,origin,phase-data,",
                "nst": 12,
                "dmin": 0.00716,
                "rms": 0.01,
                "gap": 110,
                "magType": "md",
                "type": "earthquake",
                "title": "M 0.8 - 9 km NW of The Geysers, CA"
            },
            "geometry": {
                "type": "Point",
                "coordinates": [
                    -122.844169616699,
                    38.8236656188965,
                    1.94000005722046
                ]
            },
            "id": "nc75001466"
        },
        {
            "type": "Feature",
            "properties": {
                "mag": 5.4,
                "place": "168 km WNW of Pangai, Tonga",
                "time": "2024-05-05 00:13:39.357000",
                "updated": 1714900660262,
                "tz": null,
                "url": "https://earthquake.usgs.gov/earthquakes/eventpage/us6000mwfi",
                "detail": "https://earthquake.usgs.gov/fdsnws/event/1/query?eventid=us6000mwfi&format=geojson",
                "felt": null,
                "cdi": null,
                "mmi": 3.597,
                "alert": "green",
                "status": "reviewed",
                "tsunami": 0,
                "sig": 449,
                "net": "us",
                "code": "6000mwfi",
                "ids": ",usauto6000mwfi,us6000mwfi,",
                "sources": ",usauto,us,",
                "types": ",internal-moment-tensor,losspager,origin,phase-data,shakemap,",
                "nst": 47,
                "dmin": 5.332,
                "rms": 1.04,
                "gap": 66,
                "magType": "mb",
                "type": "earthquake",
                "title": "M 5.4 - 168 km WNW of Pangai, Tonga"
            },
            "geometry": {
                "type": "Point",
                "coordinates": [
                    -175.8739,
                    -19.3097,
                    10
                ]
            },
            "id": "us6000mwfi"
        },
        {
            "type": "Feature",
            "properties": {
                "mag": 2.1,
                "place": "66 km SSW of Whites City, New Mexico",
                "time": "2024-05-05 00:02:00.042000",
                "updated": 1714894487918,
                "tz": null,
                "url": "https://earthquake.usgs.gov/earthquakes/eventpage/tx2024iuxu",
                "detail": "https://earthquake.usgs.gov/fdsnws/event/1/query?eventid=tx2024iuxu&format=geojson",
                "felt": null,
                "cdi": null,
                "mmi": null,
                "alert": null,
                "status": "automatic",
                "tsunami": 0,
                "sig": 68,
                "net": "tx",
                "code": "2024iuxu",
                "ids": ",tx2024iuxu,",
                "sources": ",tx,",
                "types": ",origin,phase-data,",
                "nst": 18,
                "dmin": 0.1,
                "rms": 0.2,
                "gap": 155,
                "magType": "ml",
                "type": "earthquake",
                "title": "M 2.1 - 66 km SSW of Whites City, New Mexico"
            },
            "geometry": {
                "type": "Point",
                "coordinates": [
                    -104.532,
                    31.591,
                    3.6563
                ]
            },
            "id": "tx2024iuxu"
        },
        {
            "type": "Feature",
            "properties": {
                "mag": 1.39,
                "place": "2 km NNE of Pinnacles, CA",
                "time": "2024-05-04 23:58:15.310000",
                "updated": 1714892392537,
                "tz": null,
                "url": "https://earthquake.usgs.gov/earthquakes/eventpage/nc75001456",
                "detail": "https://earthquake.usgs.gov/fdsnws/event/1/query?eventid=nc75001456&format=geojson",
                "felt": null,
                "cdi": null,
                "mmi": null,
                "alert": null,
                "status": "automatic",
                "tsunami": 0,
                "sig": 30,
                "net": "nc",
                "code": "75001456",
                "ids": ",nc75001456,",
                "sources": ",nc,",
                "types": ",nearby-cities,origin,phase-data,",
                "nst": 12,
                "dmin": 0.08739,
                "rms": 0.05,
                "gap": 114,
                "magType": "md",
                "type": "earthquake",
                "title": "M 1.4 - 2 km NNE of Pinnacles, CA"
            },
            "geometry": {
                "type": "Point",
                "coordinates": [
                    -121.141166687012,
                    36.5476684570312,
                    8.8100004196167
                ]
            },
            "id": "nc75001456"
        },
        {
            "type": "Feature",
            "properties": {
                "mag": 4.9,
                "place": "88 km W of Sungai Penuh, Indonesia",
                "time": "2024-05-04 23:49:00.882000",
                "updated": 1714893131040,
                "tz": null,
                "url": "https://earthquake.usgs.gov/earthquakes/eventpage/us6000mwfd",
                "detail": "https://earthquake.usgs.gov/fdsnws/event/1/query?eventid=us6000mwfd&format=geojson",
                "felt": null,
                "cdi": null,
                "mmi": null,
                "alert": null,
                "status": "reviewed",
                "tsunami": 0,
                "sig": 369,
                "net": "us",
                "code": "6000mwfd",
                "ids": ",us6000mwfd,",
                "sources": ",us,",
                "types": ",origin,phase-data,",
                "nst": 42,
                "dmin": 3.241,
                "rms": 0.57,
                "gap": 178,
                "magType": "mb",
                "type": "earthquake",
                "title": "M 4.9 - 88 km W of Sungai Penuh, Indonesia"
            },
            "geometry": {
                "type": "Point",
                "coordinates": [
                    100.5988,
                    -2.1162,
                    69.642
                ]
            },
            "id": "us6000mwfd"
        },
        {
            "type": "Feature",
            "properties": {
                "mag": 5.3,
                "place": "Kermadec Islands, New Zealand",
                "time": "2024-05-04 23:15:37.971000",
                "updated": 1714891000040,
                "tz": null,
                "url": "https://earthquake.usgs.gov/earthquakes/eventpage/us6000mwfb",
                "detail": "https://earthquake.usgs.gov/fdsnws/event/1/query?eventid=us6000mwfb&format=geojson",
                "felt": null,
                "cdi": null,
                "mmi": null,
                "alert": null,
                "status": "reviewed",
                "tsunami": 0,
                "sig": 432,
                "net": "us",
                "code": "6000mwfb",
                "ids": ",us6000mwfb,",
                "sources": ",us,",
                "types": ",origin,phase-data,",
                "nst": 77,
                "dmin": 0.644,
                "rms": 1.2,
                "gap": 51,
                "magType": "mww",
                "type": "earthquake",
                "title": "M 5.3 - Kermadec Islands, New Zealand"
            },
            "geometry": {
                "type": "Point",
                "coordinates": [
                    -178.6294,
                    -29.4481,
                    216.068
                ]
            },
            "id": "us6000mwfb"
        },
        {
            "type": "Feature",
            "properties": {
                "mag": 0.69,
                "place": "9 km WNW of Cobb, CA",
                "time": "2024-05-04 23:11:56.520000",
                "updated": 1714889611912,
                "tz": null,
                "url": "https://earthquake.usgs.gov/earthquakes/eventpage/nc75001451",
                "detail": "https://earthquake.usgs.gov/fdsnws/event/1/query?eventid=nc75001451&format=geojson",
                "felt": null,
                "cdi": null,
                "mmi": null,
                "alert": null,
                "status": "automatic",
                "tsunami": 0,
                "sig": 7,
                "net": "nc",
                "code": "75001451",
                "ids": ",nc75001451,",
                "sources": ",nc,",
                "types": ",nearby-cities,origin,phase-data,",
                "nst": 15,
                "dmin": 0.004868,
                "rms": 0.02,
                "gap": 108,
                "magType": "md",
                "type": "earthquake",
                "title": "M 0.7 - 9 km WNW of Cobb, CA"
            },
            "geometry": {
                "type": "Point",
                "coordinates": [
                    -122.829666137695,
                    38.84033203125,
                    1.30999994277954
                ]
            },
            "id": "nc75001451"
        },
        {
            "type": "Feature",
            "properties": {
                "mag": 1.9,
                "place": "70 km W of Tyonek, Alaska",
                "time": "2024-05-04 23:02:51.869000",
                "updated": 1714889177583,
                "tz": null,
                "url": "https://earthquake.usgs.gov/earthquakes/eventpage/ak0245shavaa",
                "detail": "https://earthquake.usgs.gov/fdsnws/event/1/query?eventid=ak0245shavaa&format=geojson",
                "felt": null,
                "cdi": null,
                "mmi": null,
                "alert": null,
                "status": "automatic",
                "tsunami": 0,
                "sig": 56,
                "net": "ak",
                "code": "0245shavaa",
                "ids": ",ak0245shavaa,",
                "sources": ",ak,",
                "types": ",origin,phase-data,",
                "nst": null,
                "dmin": null,
                "rms": 0.47,
                "gap": null,
                "magType": "ml",
                "type": "earthquake",
                "title": "M 1.9 - 70 km W of Tyonek, Alaska"
            },
            "geometry": {
                "type": "Point",
                "coordinates": [
                    -152.4296,
                    61.0159,
                    122.4
                ]
            },
            "id": "ak0245shavaa"
        },
        {
            "type": "Feature",
            "properties": {
                "mag": 1.99,
                "place": "15 km S of Volcano, Hawaii",
                "time": "2024-05-04 23:01:28.500000",
                "updated": 1714889045750,
                "tz": null,
                "url": "https://earthquake.usgs.gov/earthquakes/eventpage/hv74214037",
                "detail": "https://earthquake.usgs.gov/fdsnws/event/1/query?eventid=hv74214037&format=geojson",
                "felt": null,
                "cdi": null,
                "mmi": null,
                "alert": null,
                "status": "automatic",
                "tsunami": 0,
                "sig": 61,
                "net": "hv",
                "code": "74214037",
                "ids": ",hv74214037,",
                "sources": ",hv,",
                "types": ",origin,phase-data,",
                "nst": 44,
                "dmin": 0.02731,
                "rms": 0.180000007,
                "gap": 99,
                "magType": "ml",
                "type": "earthquake",
                "title": "M 2.0 - 15 km S of Volcano, Hawaii"
            },
            "geometry": {
                "type": "Point",
                "coordinates": [
                    -155.213333129883,
                    19.3064994812012,
                    1.83000004291534
                ]
            },
            "id": "hv74214037"
        },
        {
            "type": "Feature",
            "properties": {
                "mag": 1.2,
                "place": "108 km NNE of Arctic Village, Alaska",
                "time": "2024-05-04 22:53:23.521000",
                "updated": 1714893821772,
                "tz": null,
                "url": "https://earthquake.usgs.gov/earthquakes/eventpage/ak0245sh0b8g",
                "detail": "https://earthquake.usgs.gov/fdsnws/event/1/query?eventid=ak0245sh0b8g&format=geojson",
                "felt": null,
                "cdi": null,
                "mmi": null,
                "alert": null,
                "status": "reviewed",
                "tsunami": 0,
                "sig": 22,
                "net": "ak",
                "code": "0245sh0b8g",
                "ids": ",ak0245sh0b8g,",
                "sources": ",ak,",
                "types": ",origin,phase-data,",
                "nst": null,
                "dmin": null,
                "rms": 0.62,
                "gap": null,
                "magType": "ml",
                "type": "earthquake",
                "title": "M 1.2 - 108 km NNE of Arctic Village, Alaska"
            },
            "geometry": {
                "type": "Point",
                "coordinates": [
                    -144.6751,
                    69.0503,
                    3.2
                ]
            },
            "id": "ak0245sh0b8g"
        },
        {
            "type": "Feature",
            "properties": {
                "mag": 5.6,
                "place": "143 km NNE of Fais, Micronesia",
                "time": "2024-05-04 22:44:19.589000",
                "updated": 1714895668310,
                "tz": null,
                "url": "https://earthquake.usgs.gov/earthquakes/eventpage/us6000mwf5",
                "detail": "https://earthquake.usgs.gov/fdsnws/event/1/query?eventid=us6000mwf5&format=geojson",
                "felt": null,
                "cdi": null,
                "mmi": 0,
                "alert": "green",
                "status": "reviewed",
                "tsunami": 0,
                "sig": 482,
                "net": "us",
                "code": "6000mwf5",
                "ids": ",usauto6000mwf5,us6000mwf5,",
                "sources": ",usauto,us,",
                "types": ",internal-moment-tensor,losspager,oaf,origin,phase-data,shakemap,",
                "nst": 87,
                "dmin": 4.483,
                "rms": 1.28,
                "gap": 72,
                "magType": "mb",
                "type": "earthquake",
                "title": "M 5.6 - 143 km NNE of Fais, Micronesia"
            },
            "geometry": {
                "type": "Point",
                "coordinates": [
                    141.216,
                    10.8618,
                    10
                ]
            },
            "id": "us6000mwf5"
        },
        {
            "type": "Feature",
            "properties": {
                "mag": 1.2,
                "place": "6 km SSE of Meadow Lakes, Alaska",
                "time": "2024-05-04 22:39:09.563000",
                "updated": 1714887687338,
                "tz": null,
                "url": "https://earthquake.usgs.gov/earthquakes/eventpage/ak0245sgx9ws",
                "detail": "https://earthquake.usgs.gov/fdsnws/event/1/query?eventid=ak0245sgx9ws&format=geojson",
                "felt": null,
                "cdi": null,
                "mmi": null,
                "alert": null,
                "status": "automatic",
                "tsunami": 0,
                "sig": 22,
                "net": "ak",
                "code": "0245sgx9ws",
                "ids": ",ak0245sgx9ws,",
                "sources": ",ak,",
                "types": ",origin,phase-data,",
                "nst": null,
                "dmin": null,
                "rms": 0.73,
                "gap": null,
                "magType": "ml",
                "type": "earthquake",
                "title": "M 1.2 - 6 km SSE of Meadow Lakes, Alaska"
            },
            "geometry": {
                "type": "Point",
                "coordinates": [
                    -149.5625,
                    61.5698,
                    31
                ]
            },
            "id": "ak0245sgx9ws"
        },
        {
            "type": "Feature",
            "properties": {
                "mag": 2.7,
                "place": "26 km WNW of Willow, Alaska",
                "time": "2024-05-04 22:35:37.531000",
                "updated": 1714892137040,
                "tz": null,
                "url": "https://earthquake.usgs.gov/earthquakes/eventpage/ak0245sgwh7a",
                "detail": "https://earthquake.usgs.gov/fdsnws/event/1/query?eventid=ak0245sgwh7a&format=geojson",
                "felt": null,
                "cdi": null,
                "mmi": null,
                "alert": null,
                "status": "automatic",
                "tsunami": 0,
                "sig": 112,
                "net": "ak",
                "code": "0245sgwh7a",
                "ids": ",us6000mwf4,ak0245sgwh7a,",
                "sources": ",us,ak,",
                "types": ",origin,phase-data,",
                "nst": null,
                "dmin": null,
                "rms": 0.48,
                "gap": null,
                "magType": "ml",
                "type": "earthquake",
                "title": "M 2.7 - 26 km WNW of Willow, Alaska"
            },
            "geometry": {
                "type": "Point",
                "coordinates": [
                    -150.503,
                    61.8411,
                    35.7
                ]
            },
            "id": "ak0245sgwh7a"
        },
        {
            "type": "Feature",
            "properties": {
                "mag": 4.3,
                "place": "8 km ESE of Talagante, Chile",
                "time": "2024-05-04 22:31:53.206000",
                "updated": 1714898257157,
                "tz": null,
                "url": "https://earthquake.usgs.gov/earthquakes/eventpage/us6000mwf1",
                "detail": "https://earthquake.usgs.gov/fdsnws/event/1/query?eventid=us6000mwf1&format=geojson",
                "felt": 2,
                "cdi": 2.7,
                "mmi": null,
                "alert": null,
                "status": "reviewed",
                "tsunami": 0,
                "sig": 285,
                "net": "us",
                "code": "6000mwf1",
                "ids": ",us6000mwf1,",
                "sources": ",us,",
                "types": ",dyfi,origin,phase-data,",
                "nst": 31,
                "dmin": 0.159,
                "rms": 0.44,
                "gap": 60,
                "magType": "mb",
                "type": "earthquake",
                "title": "M 4.3 - 8 km ESE of Talagante, Chile"
            },
            "geometry": {
                "type": "Point",
                "coordinates": [
                    -70.8356,
                    -33.6811,
                    75.758
                ]
            },
            "id": "us6000mwf1"
        },
        {
            "type": "Feature",
            "properties": {
                "mag": 1.7,
                "place": "59 km S of Whites City, New Mexico",
                "time": "2024-05-04 22:31:49.925000",
                "updated": 1714888375211,
                "tz": null,
                "url": "https://earthquake.usgs.gov/earthquakes/eventpage/tx2024iuuw",
                "detail": "https://earthquake.usgs.gov/fdsnws/event/1/query?eventid=tx2024iuuw&format=geojson",
                "felt": null,
                "cdi": null,
                "mmi": null,
                "alert": null,
                "status": "automatic",
                "tsunami": 0,
                "sig": 44,
                "net": "tx",
                "code": "2024iuuw",
                "ids": ",tx2024iuuw,",
                "sources": ",tx,",
                "types": ",origin,phase-data,",
                "nst": 17,
                "dmin": 0,
                "rms": 0.2,
                "gap": 128,
                "magType": "ml",
                "type": "earthquake",
                "title": "M 1.7 - 59 km S of Whites City, New Mexico"
            },
            "geometry": {
                "type": "Point",
                "coordinates": [
                    -104.291,
                    31.647,
                    3.9611
                ]
            },
            "id": "tx2024iuuw"
        },
        {
            "type": "Feature",
            "properties": {
                "mag": 1.31,
                "place": "12 km NE of Ojai, CA",
                "time": "2024-05-04 22:25:33.750000",
                "updated": 1714887150571,
                "tz": null,
                "url": "https://earthquake.usgs.gov/earthquakes/eventpage/ci40739808",
                "detail": "https://earthquake.usgs.gov/fdsnws/event/1/query?eventid=ci40739808&format=geojson",
                "felt": null,
                "cdi": null,
                "mmi": null,
                "alert": null,
                "status": "automatic",
                "tsunami": 0,
                "sig": 26,
                "net": "ci",
                "code": "40739808",
                "ids": ",ci40739808,",
                "sources": ",ci,",
                "types": ",nearby-cities,origin,phase-data,scitech-link,",
                "nst": 35,
                "dmin": 0.07492,
                "rms": 0.27,
                "gap": 40,
                "magType": "ml",
                "type": "earthquake",
                "title": "M 1.3 - 12 km NE of Ojai, CA"
            },
            "geometry": {
                "type": "Point",
                "coordinates": [
                    -119.1396667,
                    34.512,
                    0.16
                ]
            },
            "id": "ci40739808"
        },
        {
            "type": "Feature",
            "properties": {
                "mag": 1.78,
                "place": "2 km N of Colton, CA",
                "time": "2024-05-04 22:22:11.870000",
                "updated": 1714887205450,
                "tz": null,
                "url": "https://earthquake.usgs.gov/earthquakes/eventpage/ci40739792",
                "detail": "https://earthquake.usgs.gov/fdsnws/event/1/query?eventid=ci40739792&format=geojson",
                "felt": null,
                "cdi": null,
                "mmi": null,
                "alert": null,
                "status": "automatic",
                "tsunami": 0,
                "sig": 49,
                "net": "ci",
                "code": "40739792",
                "ids": ",ci40739792,",
                "sources": ",ci,",
                "types": ",focal-mechanism,nearby-cities,origin,phase-data,scitech-link,",
                "nst": 93,
                "dmin": 0.02451,
                "rms": 0.18,
                "gap": 32,
                "magType": "ml",
                "type": "earthquake",
                "title": "M 1.8 - 2 km N of Colton, CA"
            },
            "geometry": {
                "type": "Point",
                "coordinates": [
                    -117.31,
                    34.0956667,
                    16.31
                ]
            },
            "id": "ci40739792"
        },
        {
            "type": "Feature",
            "properties": {
                "mag": 1.21,
                "place": "11 km NE of Ojai, CA",
                "time": "2024-05-04 22:19:22.680000",
                "updated": 1714886799164,
                "tz": null,
                "url": "https://earthquake.usgs.gov/earthquakes/eventpage/ci40739784",
                "detail": "https://earthquake.usgs.gov/fdsnws/event/1/query?eventid=ci40739784&format=geojson",
                "felt": null,
                "cdi": null,
                "mmi": null,
                "alert": null,
                "status": "automatic",
                "tsunami": 0,
                "sig": 23,
                "net": "ci",
                "code": "40739784",
                "ids": ",ci40739784,",
                "sources": ",ci,",
                "types": ",nearby-cities,origin,phase-data,scitech-link,",
                "nst": 9,
                "dmin": 0.07209,
                "rms": 0.14,
                "gap": 97,
                "magType": "ml",
                "type": "earthquake",
                "title": "M 1.2 - 11 km NE of Ojai, CA"
            },
            "geometry": {
                "type": "Point",
                "coordinates": [
                    -119.1436667,
                    34.509,
                    -0.47
                ]
            },
            "id": "ci40739784"
        }
    ],
    "metadata": {
        "lastUpdated": "2024-05-05T02:53:09",
        "url": "https://earthquake.usgs.gov/fdsnws/event/1/query?format=geojson&starttime=2024-05-05T00:00:00",
        "title": "USGS Earthquakes",
        "status": 200,
        "count": 39
    },
    "type": "FeatureCollection"
}