{
    "features": [
        {
            "type": "Feature",
            "properties": {
                "mag": 1.4,
                "place": "45 km SE of Denali National Park, Alaska",
                "time": "2024-05-08 23:13:08.114000",
                "updated": 1715235320757,
                "tz": null,
                "url": "https://earthquake.usgs.gov/earthquakes/eventpage/ak0245z3iirf",
                "detail": "https://earthquake.usgs.gov/fdsnws/event/1/query?eventid=ak0245z3iirf&format=geojson",
                "felt": null,
                "cdi": null,
                "mmi": null,
                "alert": null,
                "status": "automatic",
                "tsunami": 0,
                "sig": 30,
                "net": "ak",
                "code": "0245z3iirf",
                "ids": ",ak0245z3iirf,",
                "sources": ",ak,",
                "types": ",origin,phase-data,",
                "nst": null,
                "dmin": null,
                "rms": 0.52,
                "gap": null,
                "magType": "ml",
                "type": "earthquake",
                "title": "M 1.4 - 45 km SE of Denali National Park, Alaska"
            },
            "geometry": {
                "type": "Point",
                "coordinates": [
                    -151.1121,
                    63.2354,
                    14.3
                ]
            },
            "id": "ak0245z3iirf"
        },
        {
            "type": "Feature",
            "properties": {
                "mag": 0.8,
                "place": "7 km S of Salcha, Alaska",
                "time": "2024-05-08 22:52:31.881000",
                "updated": 1715234091423,
                "tz": null,
                "url": "https://earthquake.usgs.gov/earthquakes/eventpage/ak0245z35hxh",
                "detail": "https://earthquake.usgs.gov/fdsnws/event/1/query?eventid=ak0245z35hxh&format=geojson",
                "felt": null,
                "cdi": null,
                "mmi": null,
                "alert": null,
                "status": "automatic",
                "tsunami": 0,
                "sig": 10,
                "net": "ak",
                "code": "0245z35hxh",
                "ids": ",ak0245z35hxh,",
                "sources": ",ak,",
                "types": ",origin,phase-data,",
                "nst": null,
                "dmin": null,
                "rms": 0.68,
                "gap": null,
                "magType": "ml",
                "type": "earthquake",
                "title": "M 0.8 - 7 km S of Salcha, Alaska"
            },
            "geometry": {
                "type": "Point",
                "coordinates": [
                    -146.9267,
                    64.4558,
                    10.4
                ]
            },
            "id": "ak0245z35hxh"
        },
        {
            "type": "Feature",
            "properties": {
                "mag": 1.26,
                "place": "8 km SW of Corona, CA",
                "time": "2024-05-08 22:49:48.200000",
                "updated": 1715234438870,
                "tz": null,
                "url": "https://earthquake.usgs.gov/earthquakes/eventpage/ci40743568",
                "detail": "https://earthquake.usgs.gov/fdsnws/event/1/query?eventid=ci40743568&format=geojson",
                "felt": null,
                "cdi": null,
                "mmi": null,
                "alert": null,
                "status": "automatic",
                "tsunami": 0,
                "sig": 24,
                "net": "ci",
                "code": "40743568",
                "ids": ",ci40743568,",
                "sources": ",ci,",
                "types": ",focal-mechanism,nearby-cities,origin,phase-data,scitech-link,",
                "nst": 45,
                "dmin": 0.03204,
                "rms": 0.19,
                "gap": 58,
                "magType": "ml",
                "type": "earthquake",
                "title": "M 1.3 - 8 km SW of Corona, CA"
            },
            "geometry": {
                "type": "Point",
                "coordinates": [
                    -117.6356667,
                    33.8185,
                    3.68
                ]
            },
            "id": "ci40743568"
        },
        {
            "type": "Feature",
            "properties": {
                "mag": 1.8,
                "place": "11 km W of Fishhook, Alaska",
                "time": "2024-05-08 22:47:24.024000",
                "updated": 1715233783313,
                "tz": null,
                "url": "https://earthquake.usgs.gov/earthquakes/eventpage/ak0245z34eqa",
                "detail": "https://earthquake.usgs.gov/fdsnws/event/1/query?eventid=ak0245z34eqa&format=geojson",
                "felt": null,
                "cdi": null,
                "mmi": null,
                "alert": null,
                "status": "automatic",
                "tsunami": 0,
                "sig": 50,
                "net": "ak",
                "code": "0245z34eqa",
                "ids": ",ak0245z34eqa,",
                "sources": ",ak,",
                "types": ",origin,phase-data,",
                "nst": null,
                "dmin": null,
                "rms": 0.59,
                "gap": null,
                "magType": "ml",
                "type": "earthquake",
                "title": "M 1.8 - 11 km W of Fishhook, Alaska"
            },
            "geometry": {
                "type": "Point",
                "coordinates": [
                    -149.452,
                    61.7392,
                    30.4
                ]
            },
            "id": "ak0245z34eqa"
        },
        {
            "type": "Feature",
            "properties": {
                "mag": 1.7,
                "place": "48 km WNW of Aleneva, Alaska",
                "time": "2024-05-08 22:39:39.998000",
                "updated": 1715233286757,
                "tz": null,
                "url": "https://earthquake.usgs.gov/earthquakes/eventpage/ak0245z32q8f",
                "detail": "https://earthquake.usgs.gov/fdsnws/event/1/query?eventid=ak0245z32q8f&format=geojson",
                "felt": null,
                "cdi": null,
                "mmi": null,
                "alert": null,
                "status": "automatic",
                "tsunami": 0,
                "sig": 44,
                "net": "ak",
                "code": "0245z32q8f",
                "ids": ",ak0245z32q8f,",
                "sources": ",ak,",
                "types": ",origin,phase-data,",
                "nst": null,
                "dmin": null,
                "rms": 0.19,
                "gap": null,
                "magType": "ml",
                "type": "earthquake",
                "title": "M 1.7 - 48 km WNW of Aleneva, Alaska"
            },
            "geometry": {
                "type": "Point",
                "coordinates": [
                    -153.6457,
                    58.2641,
                    73.2
                ]
            },
            "id": "ak0245z32q8f"
        },
        {
            "type": "Feature",
            "properties": {
                "mag": 0.76,
                "place": "7 km WNW of Cobb, CA",
                "time": "2024-05-08 22:31:57.080000",
                "updated": 1715232812873,
                "tz": null,
                "url": "https://earthquake.usgs.gov/earthquakes/eventpage/nc75003666",
                "detail": "https://earthquake.usgs.gov/fdsnws/event/1/query?eventid=nc75003666&format=geojson",
                "felt": null,
                "cdi": null,
                "mmi": null,
                "alert": null,
                "status": "automatic",
                "tsunami": 0,
                "sig": 9,
                "net": "nc",
                "code": "75003666",
                "ids": ",nc75003666,",
                "sources": ",nc,",
                "types": ",nearby-cities,origin,phase-data,",
                "nst": 12,
                "dmin": 0.007282,
                "rms": 0.02,
                "gap": 74,
                "magType": "md",
                "type": "earthquake",
                "title": "M 0.8 - 7 km WNW of Cobb, CA"
            },
            "geometry": {
                "type": "Point",
                "coordinates": [
                    -122.804664611816,
                    38.8293342590332,
                    1.41999995708466
                ]
            },
            "id": "nc75003666"
        },
        {
            "type": "Feature",
            "properties": {
                "mag": 1.3,
                "place": "73 km W of Salamatof, Alaska",
                "time": "2024-05-08 22:22:52.587000",
                "updated": 1715232249313,
                "tz": null,
                "url": "https://earthquake.usgs.gov/earthquakes/eventpage/ak0245z2z416",
                "detail": "https://earthquake.usgs.gov/fdsnws/event/1/query?eventid=ak0245z2z416&format=geojson",
                "felt": null,
                "cdi": null,
                "mmi": null,
                "alert": null,
                "status": "automatic",
                "tsunami": 0,
                "sig": 26,
                "net": "ak",
                "code": "0245z2z416",
                "ids": ",ak0245z2z416,",
                "sources": ",ak,",
                "types": ",origin,phase-data,",
                "nst": null,
                "dmin": null,
                "rms": 0.14,
                "gap": null,
                "magType": "ml",
                "type": "earthquake",
                "title": "M 1.3 - 73 km W of Salamatof, Alaska"
            },
            "geometry": {
                "type": "Point",
                "coordinates": [
                    -152.6583,
                    60.7015,
                    15
                ]
            },
            "id": "ak0245z2z416"
        },
        {
            "type": "Feature",
            "properties": {
                "mag": 1.51,
                "place": "4 km NNW of The Geysers, CA",
                "time": "2024-05-08 22:22:51.630000",
                "updated": 1715232268777,
                "tz": null,
                "url": "https://earthquake.usgs.gov/earthquakes/eventpage/nc75003661",
                "detail": "https://earthquake.usgs.gov/fdsnws/event/1/query?eventid=nc75003661&format=geojson",
                "felt": null,
                "cdi": null,
                "mmi": null,
                "alert": null,
                "status": "automatic",
                "tsunami": 0,
                "sig": 35,
                "net": "nc",
                "code": "75003661",
                "ids": ",nc75003661,",
                "sources": ",nc,",
                "types": ",nearby-cities,origin,phase-data,",
                "nst": 26,
                "dmin": 0.009158,
                "rms": 0.04,
                "gap": 67,
                "magType": "md",
                "type": "earthquake",
                "title": "M 1.5 - 4 km NNW of The Geysers, CA"
            },
            "geometry": {
                "type": "Point",
                "coordinates": [
                    -122.779167175293,
                    38.8041648864746,
                    2.60999989509583
                ]
            },
            "id": "nc75003661"
        },
        {
            "type": "Feature",
            "properties": {
                "mag": 1.3,
                "place": "18 km NNE of Chickaloon, Alaska",
                "time": "2024-05-08 22:16:44.068000",
                "updated": 1715231943522,
                "tz": null,
                "url": "https://earthquake.usgs.gov/earthquakes/eventpage/ak0245z2xt28",
                "detail": "https://earthquake.usgs.gov/fdsnws/event/1/query?eventid=ak0245z2xt28&format=geojson",
                "felt": null,
                "cdi": null,
                "mmi": null,
                "alert": null,
                "status": "automatic",
                "tsunami": 0,
                "sig": 26,
                "net": "ak",
                "code": "0245z2xt28",
                "ids": ",ak0245z2xt28,",
                "sources": ",ak,",
                "types": ",origin,phase-data,",
                "nst": null,
                "dmin": null,
                "rms": 0.93,
                "gap": null,
                "magType": "ml",
                "type": "earthquake",
                "title": "M 1.3 - 18 km NNE of Chickaloon, Alaska"
            },
            "geometry": {
                "type": "Point",
                "coordinates": [
                    -148.3925,
                    61.9632,
                    32.8
                ]
            },
            "id": "ak0245z2xt28"
        },
        {
            "type": "Feature",
            "properties": {
                "mag": 1.21,
                "place": "10 km NNW of Anza, CA",
                "time": "2024-05-08 22:15:18.930000",
                "updated": 1715232367410,
                "tz": null,
                "url": "https://earthquake.usgs.gov/earthquakes/eventpage/ci40743560",
                "detail": "https://earthquake.usgs.gov/fdsnws/event/1/query?eventid=ci40743560&format=geojson",
                "felt": null,
                "cdi": null,
                "mmi": null,
                "alert": null,
                "status": "automatic",
                "tsunami": 0,
                "sig": 23,
                "net": "ci",
                "code": "40743560",
                "ids": ",ci40743560,",
                "sources": ",ci,",
                "types": ",focal-mechanism,nearby-cities,origin,phase-data,scitech-link,",
                "nst": 64,
                "dmin": 0.0454,
                "rms": 0.18,
                "gap": 36,
                "magType": "ml",
                "type": "earthquake",
                "title": "M 1.2 - 10 km NNW of Anza, CA"
            },
            "geometry": {
                "type": "Point",
                "coordinates": [
                    -116.7163333,
                    33.6405,
                    12.08
                ]
            },
            "id": "ci40743560"
        },
        {
            "type": "Feature",
            "properties": {
                "mag": 0.96,
                "place": "10 km SW of Idyllwild, CA",
                "time": "2024-05-08 21:57:41.540000",
                "updated": 1715231033733,
                "tz": null,
                "url": "https://earthquake.usgs.gov/earthquakes/eventpage/ci40743552",
                "detail": "https://earthquake.usgs.gov/fdsnws/event/1/query?eventid=ci40743552&format=geojson",
                "felt": null,
                "cdi": null,
                "mmi": null,
                "alert": null,
                "status": "automatic",
                "tsunami": 0,
                "sig": 14,
                "net": "ci",
                "code": "40743552",
                "ids": ",ci40743552,",
                "sources": ",ci,",
                "types": ",nearby-cities,origin,phase-data,scitech-link,",
                "nst": 52,
                "dmin": 0.07891,
                "rms": 0.15,
                "gap": 55,
                "magType": "ml",
                "type": "earthquake",
                "title": "M 1.0 - 10 km SW of Idyllwild, CA"
            },
            "geometry": {
                "type": "Point",
                "coordinates": [
                    -116.7961667,
                    33.6716667,
                    13.6
                ]
            },
            "id": "ci40743552"
        },
        {
            "type": "Feature",
            "properties": {
                "mag": 2,
                "place": "47 km SSE of Nelchina, Alaska",
                "time": "2024-05-08 21:52:50.846000",
                "updated": 1715230481696,
                "tz": null,
                "url": "https://earthquake.usgs.gov/earthquakes/eventpage/ak0245z2k3rw",
                "detail": "https://earthquake.usgs.gov/fdsnws/event/1/query?eventid=ak0245z2k3rw&format=geojson",
                "felt": null,
                "cdi": null,
                "mmi": null,
                "alert": null,
                "status": "automatic",
                "tsunami": 0,
                "sig": 62,
                "net": "ak",
                "code": "0245z2k3rw",
                "ids": ",ak0245z2k3rw,",
                "sources": ",ak,",
                "types": ",origin,phase-data,",
                "nst": null,
                "dmin": null,
                "rms": 0.73,
                "gap": null,
                "magType": "ml",
                "type": "earthquake",
                "title": "M 2.0 - 47 km SSE of Nelchina, Alaska"
            },
            "geometry": {
                "type": "Point",
                "coordinates": [
                    -146.496,
                    61.5838,
                    29.7
                ]
            },
            "id": "ak0245z2k3rw"
        },
        {
            "type": "Feature",
            "properties": {
                "mag": 1.7,
                "place": "67 km N of Petersville, Alaska",
                "time": "2024-05-08 21:46:48.802000",
                "updated": 1715230158132,
                "tz": null,
                "url": "https://earthquake.usgs.gov/earthquakes/eventpage/ak0245z2itbk",
                "detail": "https://earthquake.usgs.gov/fdsnws/event/1/query?eventid=ak0245z2itbk&format=geojson",
                "felt": null,
                "cdi": null,
                "mmi": null,
                "alert": null,
                "status": "automatic",
                "tsunami": 0,
                "sig": 44,
                "net": "ak",
                "code": "0245z2itbk",
                "ids": ",ak0245z2itbk,",
                "sources": ",ak,",
                "types": ",origin,phase-data,",
                "nst": null,
                "dmin": null,
                "rms": 0.51,
                "gap": null,
                "magType": "ml",
                "type": "earthquake",
                "title": "M 1.7 - 67 km N of Petersville, Alaska"
            },
            "geometry": {
                "type": "Point",
                "coordinates": [
                    -150.5528,
                    63.0931,
                    95.9
                ]
            },
            "id": "ak0245z2itbk"
        },
        {
            "type": "Feature",
            "properties": {
                "mag": 1.27,
                "place": "5 km NE of Hollister, CA",
                "time": "2024-05-08 21:33:40.450000",
                "updated": 1715229316095,
                "tz": null,
                "url": "https://earthquake.usgs.gov/earthquakes/eventpage/nc75003656",
                "detail": "https://earthquake.usgs.gov/fdsnws/event/1/query?eventid=nc75003656&format=geojson",
                "felt": null,
                "cdi": null,
                "mmi": null,
                "alert": null,
                "status": "automatic",
                "tsunami": 0,
                "sig": 25,
                "net": "nc",
                "code": "75003656",
                "ids": ",nc75003656,",
                "sources": ",nc,",
                "types": ",nearby-cities,origin,phase-data,",
                "nst": 8,
                "dmin": 0.05321,
                "rms": 0.09,
                "gap": 121,
                "magType": "md",
                "type": "earthquake",
                "title": "M 1.3 - 5 km NE of Hollister, CA"
            },
            "geometry": {
                "type": "Point",
                "coordinates": [
                    -121.361000061035,
                    36.882999420166,
                    6.26000022888184
                ]
            },
            "id": "nc75003656"
        },
        {
            "type": "Feature",
            "properties": {
                "mag": 0.75,
                "place": "7 km WNW of Cobb, CA",
                "time": "2024-05-08 21:30:06.240000",
                "updated": 1715229101015,
                "tz": null,
                "url": "https://earthquake.usgs.gov/earthquakes/eventpage/nc75003651",
                "detail": "https://earthquake.usgs.gov/fdsnws/event/1/query?eventid=nc75003651&format=geojson",
                "felt": null,
                "cdi": null,
                "mmi": null,
                "alert": null,
                "status": "automatic",
                "tsunami": 0,
                "sig": 9,
                "net": "nc",
                "code": "75003651",
                "ids": ",nc75003651,",
                "sources": ",nc,",
                "types": ",nearby-cities,origin,phase-data,",
                "nst": 9,
                "dmin": 0.008417,
                "rms": 0.01,
                "gap": 74,
                "magType": "md",
                "type": "earthquake",
                "title": "M 0.8 - 7 km WNW of Cobb, CA"
            },
            "geometry": {
                "type": "Point",
                "coordinates": [
                    -122.801498413086,
                    38.828498840332,
                    1.58000004291534
                ]
            },
            "id": "nc75003651"
        }
    ],
    "metadata": {
        "lastUpdated": "2024-05-08T23:15:33",
        "url": "https://earthquake.usgs.gov/fdsnws/event/1/query?format=geojson&starttime=2024-05-08T00:00:00",
        "title": "USGS Earthquakes",
        "status": 200,
        "count": 15
    },
    "type": "FeatureCollection"
}